{"errors":[],"warnings":[],"namedChunkGroups":{"polyfill":{"chunks":[4,15],"assets":["webpack-runtime-ff5fb5116c26a2de4150.js","webpack-runtime-ff5fb5116c26a2de4150.js.map","polyfill-b398b3ae0b1ff5b45fc5.js","polyfill-b398b3ae0b1ff5b45fc5.js.map"],"children":{},"childAssets":{}},"app":{"chunks":[4,0,14,5],"assets":["webpack-runtime-ff5fb5116c26a2de4150.js","webpack-runtime-ff5fb5116c26a2de4150.js.map","styles.c3084eacb2dde46e6aba.css","styles-407fe62976dc5310c43e.js","styles-407fe62976dc5310c43e.js.map","framework-5a1b297d9adac74fe592.js","framework-5a1b297d9adac74fe592.js.map","app-97e75b8b255d425b3b8f.js","app-97e75b8b255d425b3b8f.js.map"],"children":{},"childAssets":{}},"component---src-pages-404-js":{"chunks":[0,1,2,6],"assets":["styles.c3084eacb2dde46e6aba.css","styles-407fe62976dc5310c43e.js","styles-407fe62976dc5310c43e.js.map","cb1608f2-449a62c70e6a52447c77.js","cb1608f2-449a62c70e6a52447c77.js.map","commons-05b335316f7b6eafd5e3.js","commons-05b335316f7b6eafd5e3.js.map","component---src-pages-404-js-0200d329274f2beb1f1f.js","component---src-pages-404-js-0200d329274f2beb1f1f.js.map"],"children":{},"childAssets":{}},"component---src-pages-about-js":{"chunks":[0,1,2,7],"assets":["styles.c3084eacb2dde46e6aba.css","styles-407fe62976dc5310c43e.js","styles-407fe62976dc5310c43e.js.map","cb1608f2-449a62c70e6a52447c77.js","cb1608f2-449a62c70e6a52447c77.js.map","commons-05b335316f7b6eafd5e3.js","commons-05b335316f7b6eafd5e3.js.map","component---src-pages-about-js-74e9e2a7a51ae9383ef0.js","component---src-pages-about-js-74e9e2a7a51ae9383ef0.js.map"],"children":{},"childAssets":{}},"component---src-pages-apply-js":{"chunks":[0,1,2,8],"assets":["styles.c3084eacb2dde46e6aba.css","styles-407fe62976dc5310c43e.js","styles-407fe62976dc5310c43e.js.map","cb1608f2-449a62c70e6a52447c77.js","cb1608f2-449a62c70e6a52447c77.js.map","commons-05b335316f7b6eafd5e3.js","commons-05b335316f7b6eafd5e3.js.map","component---src-pages-apply-js-381e993cc915a48c3ab0.js","component---src-pages-apply-js-381e993cc915a48c3ab0.js.map"],"children":{},"childAssets":{}},"component---src-pages-faq-js":{"chunks":[0,1,2,9],"assets":["styles.c3084eacb2dde46e6aba.css","styles-407fe62976dc5310c43e.js","styles-407fe62976dc5310c43e.js.map","cb1608f2-449a62c70e6a52447c77.js","cb1608f2-449a62c70e6a52447c77.js.map","commons-05b335316f7b6eafd5e3.js","commons-05b335316f7b6eafd5e3.js.map","component---src-pages-faq-js-5876b5cffa888e6bc6d7.js","component---src-pages-faq-js-5876b5cffa888e6bc6d7.js.map"],"children":{},"childAssets":{}},"component---src-pages-index-js":{"chunks":[0,1,2,3,10],"assets":["styles.c3084eacb2dde46e6aba.css","styles-407fe62976dc5310c43e.js","styles-407fe62976dc5310c43e.js.map","cb1608f2-449a62c70e6a52447c77.js","cb1608f2-449a62c70e6a52447c77.js.map","commons-05b335316f7b6eafd5e3.js","commons-05b335316f7b6eafd5e3.js.map","88a7358e782852928ba8308ee23660be9e94ffbf-06efd60af0d3ae1809a9.js","88a7358e782852928ba8308ee23660be9e94ffbf-06efd60af0d3ae1809a9.js.map","component---src-pages-index-js-dffc777f89a613d0c97b.js","component---src-pages-index-js-dffc777f89a613d0c97b.js.map"],"children":{},"childAssets":{}},"component---src-pages-program-js":{"chunks":[0,1,2,11],"assets":["styles.c3084eacb2dde46e6aba.css","styles-407fe62976dc5310c43e.js","styles-407fe62976dc5310c43e.js.map","cb1608f2-449a62c70e6a52447c77.js","cb1608f2-449a62c70e6a52447c77.js.map","commons-05b335316f7b6eafd5e3.js","commons-05b335316f7b6eafd5e3.js.map","component---src-pages-program-js-5e97776ee19f313aa375.js","component---src-pages-program-js-5e97776ee19f313aa375.js.map"],"children":{},"childAssets":{}},"component---src-pages-support-us-js":{"chunks":[0,1,2,3,12],"assets":["styles.c3084eacb2dde46e6aba.css","styles-407fe62976dc5310c43e.js","styles-407fe62976dc5310c43e.js.map","cb1608f2-449a62c70e6a52447c77.js","cb1608f2-449a62c70e6a52447c77.js.map","commons-05b335316f7b6eafd5e3.js","commons-05b335316f7b6eafd5e3.js.map","88a7358e782852928ba8308ee23660be9e94ffbf-06efd60af0d3ae1809a9.js","88a7358e782852928ba8308ee23660be9e94ffbf-06efd60af0d3ae1809a9.js.map","component---src-pages-support-us-js-21bc944d29dbf6f766c8.js","component---src-pages-support-us-js-21bc944d29dbf6f766c8.js.map"],"children":{},"childAssets":{}},"component---src-pages-volunteer-js":{"chunks":[0,1,2,13],"assets":["styles.c3084eacb2dde46e6aba.css","styles-407fe62976dc5310c43e.js","styles-407fe62976dc5310c43e.js.map","cb1608f2-449a62c70e6a52447c77.js","cb1608f2-449a62c70e6a52447c77.js.map","commons-05b335316f7b6eafd5e3.js","commons-05b335316f7b6eafd5e3.js.map","component---src-pages-volunteer-js-b1e3401e59f8bf6cb5b8.js","component---src-pages-volunteer-js-b1e3401e59f8bf6cb5b8.js.map"],"children":{},"childAssets":{}}},"assetsByChunkName":{"polyfill":["webpack-runtime-ff5fb5116c26a2de4150.js","polyfill-b398b3ae0b1ff5b45fc5.js"],"app":["webpack-runtime-ff5fb5116c26a2de4150.js","styles.c3084eacb2dde46e6aba.css","styles-407fe62976dc5310c43e.js","framework-5a1b297d9adac74fe592.js","app-97e75b8b255d425b3b8f.js"],"component---src-pages-404-js":["styles.c3084eacb2dde46e6aba.css","styles-407fe62976dc5310c43e.js","cb1608f2-449a62c70e6a52447c77.js","commons-05b335316f7b6eafd5e3.js","component---src-pages-404-js-0200d329274f2beb1f1f.js"],"component---src-pages-about-js":["styles.c3084eacb2dde46e6aba.css","styles-407fe62976dc5310c43e.js","cb1608f2-449a62c70e6a52447c77.js","commons-05b335316f7b6eafd5e3.js","component---src-pages-about-js-74e9e2a7a51ae9383ef0.js"],"component---src-pages-apply-js":["styles.c3084eacb2dde46e6aba.css","styles-407fe62976dc5310c43e.js","cb1608f2-449a62c70e6a52447c77.js","commons-05b335316f7b6eafd5e3.js","component---src-pages-apply-js-381e993cc915a48c3ab0.js"],"component---src-pages-faq-js":["styles.c3084eacb2dde46e6aba.css","styles-407fe62976dc5310c43e.js","cb1608f2-449a62c70e6a52447c77.js","commons-05b335316f7b6eafd5e3.js","component---src-pages-faq-js-5876b5cffa888e6bc6d7.js"],"component---src-pages-index-js":["styles.c3084eacb2dde46e6aba.css","styles-407fe62976dc5310c43e.js","cb1608f2-449a62c70e6a52447c77.js","commons-05b335316f7b6eafd5e3.js","88a7358e782852928ba8308ee23660be9e94ffbf-06efd60af0d3ae1809a9.js","component---src-pages-index-js-dffc777f89a613d0c97b.js"],"component---src-pages-program-js":["styles.c3084eacb2dde46e6aba.css","styles-407fe62976dc5310c43e.js","cb1608f2-449a62c70e6a52447c77.js","commons-05b335316f7b6eafd5e3.js","component---src-pages-program-js-5e97776ee19f313aa375.js"],"component---src-pages-support-us-js":["styles.c3084eacb2dde46e6aba.css","styles-407fe62976dc5310c43e.js","cb1608f2-449a62c70e6a52447c77.js","commons-05b335316f7b6eafd5e3.js","88a7358e782852928ba8308ee23660be9e94ffbf-06efd60af0d3ae1809a9.js","component---src-pages-support-us-js-21bc944d29dbf6f766c8.js"],"component---src-pages-volunteer-js":["styles.c3084eacb2dde46e6aba.css","styles-407fe62976dc5310c43e.js","cb1608f2-449a62c70e6a52447c77.js","commons-05b335316f7b6eafd5e3.js","component---src-pages-volunteer-js-b1e3401e59f8bf6cb5b8.js"]}}